sales.py
settings.py
sales_module-0.0.1.dist-info/METADATA
sales_module-0.0.1.dist-info/WHEEL
sales_module-0.0.1.dist-info/licenses/LICENSE
sales_module-0.0.1.dist-info/RECORD
