Metadata-Version: 2.1
Name: sales_module
Version: 0.0.1
Summary: My customized ORM on Sales
Project-URL: Homepage, https://github.com/carlota-upm/IBD
Project-URL: Bug Tracker, https://github.com/carlota-upm/IBD/issues
Author-email: carlota-upm <carlota.medrano@alumnos.upm.es>
License-File: LICENSE
Classifier: License :: OSI Approved :: MIT License
Classifier: Operating System :: OS Independent
Classifier: Programming Language :: Python :: 3
Requires-Python: >=3.9
